src/kumaone/__about__.py
src/kumaone/__init__.py
src/kumaone/configs.py
src/kumaone/connection.py
src/kumaone/event_handlers.py
src/kumaone/ioevents.py
src/kumaone/main.py
src/kumaone/monitors.py
src/kumaone/notification_settings.py
src/kumaone/notifications.py
src/kumaone/payload_handler.py
src/kumaone/settings.py
src/kumaone/status_pages.py
src/kumaone/utils.py
src/kumaone/cli/__init__.py
src/kumaone/cli/config_cli.py
src/kumaone/cli/monitor_cli.py
src/kumaone/cli/notification_cli.py
src/kumaone/cli/status_page_cli.py
kumaone-0.0.1a10.dist-info/METADATA
kumaone-0.0.1a10.dist-info/WHEEL
kumaone-0.0.1a10.dist-info/entry_points.txt
kumaone-0.0.1a10.dist-info/licenses/AUTHORS.md
kumaone-0.0.1a10.dist-info/licenses/LICENSE
kumaone-0.0.1a10.dist-info/RECORD
