Metadata-Version: 2.3
Name: kumaone
Version: 0.0.1a10
Summary: Automation friendly bulk action CLI helper for Uptime Kuma.
Project-URL: Documentation, https://kumaone.rtfd.io/
Project-URL: Issues, https://github.com/dalwar23/kumaone/issues
Project-URL: Source, https://github.com/dalwar23/kumaone
Author-email: Dalwar Hossain <dalwar23@pm.me>
License: BSD-3-Clause
Keywords: cli,kuma,kumaone,monitoring,python3,uptime-kuma
Classifier: Development Status :: 3 - Alpha
Classifier: Environment :: Console
Classifier: License :: OSI Approved
Classifier: Programming Language :: Python
Classifier: Programming Language :: Python :: 3.9
Classifier: Programming Language :: Python :: 3.10
Classifier: Programming Language :: Python :: 3.11
Classifier: Programming Language :: Python :: 3.12
Classifier: Programming Language :: Python :: Implementation :: PyPy
Requires-Python: >=3.9
Requires-Dist: colorama>=0.4.6
Requires-Dist: python-socketio[client]>=5.11.0
Requires-Dist: pyyaml>=6.0.1
Requires-Dist: requests>=2.31.0
Requires-Dist: typer>=0.12.3
Requires-Dist: validators>=0.22.0
